odoo/addons/account_move_line_reconcile_manual/README.rst
odoo/addons/account_move_line_reconcile_manual/__init__.py
odoo/addons/account_move_line_reconcile_manual/__manifest__.py
odoo/addons/account_move_line_reconcile_manual/i18n/account_move_line_reconcile_manual.pot
odoo/addons/account_move_line_reconcile_manual/i18n/es.po
odoo/addons/account_move_line_reconcile_manual/i18n/sv.po
odoo/addons/account_move_line_reconcile_manual/readme/CONTRIBUTORS.rst
odoo/addons/account_move_line_reconcile_manual/readme/DESCRIPTION.rst
odoo/addons/account_move_line_reconcile_manual/security/ir.model.access.csv
odoo/addons/account_move_line_reconcile_manual/static/description/icon.png
odoo/addons/account_move_line_reconcile_manual/static/description/index.html
odoo/addons/account_move_line_reconcile_manual/static/description/sshot_full_rec.png
odoo/addons/account_move_line_reconcile_manual/static/description/sshot_partial_rec.png
odoo/addons/account_move_line_reconcile_manual/static/description/sshot_rec_writeoff.png
odoo/addons/account_move_line_reconcile_manual/tests/__init__.py
odoo/addons/account_move_line_reconcile_manual/tests/test_reconcile_manual.py
odoo/addons/account_move_line_reconcile_manual/views/account_move_line.xml
odoo/addons/account_move_line_reconcile_manual/wizards/__init__.py
odoo/addons/account_move_line_reconcile_manual/wizards/account_move_line_reconcile_manual.py
odoo/addons/account_move_line_reconcile_manual/wizards/account_move_line_reconcile_manual_view.xml
odoo14_addon_account_move_line_reconcile_manual-14.0.1.0.1.dev8.dist-info/METADATA
odoo14_addon_account_move_line_reconcile_manual-14.0.1.0.1.dev8.dist-info/WHEEL
odoo14_addon_account_move_line_reconcile_manual-14.0.1.0.1.dev8.dist-info/top_level.txt
odoo14_addon_account_move_line_reconcile_manual-14.0.1.0.1.dev8.dist-info/RECORD
